{
  "events": [
    {
      "title": "Bob_Research_2025-03-20",
      "start": "2025-03-20T00:00:00",
      "end": "2025-03-20T01:00:00",
      "type": "task",
      "color": "#10b981",
      "description": "Daily brief: Bob_Research_2025-03-20.md",
      "file": "Bob_Research_2025-03-20.md",
      "id": "event-c63fce2e",
      "date": "2025-03-20",
      "source": "obsidian"
    },
    {
      "title": "Chat_Migration_2026-03-15",
      "start": "2026-03-15T00:00:00",
      "end": "2026-03-15T01:00:00",
      "type": "task",
      "color": "#10b981",
      "description": "Daily brief: Chat_Migration_2026-03-15.md",
      "file": "Chat_Migration_2026-03-15.md",
      "id": "event-3eee7fbc",
      "date": "2026-03-15",
      "source": "obsidian"
    },
    {
      "title": "Morning_Brief_2026-03-15",
      "start": "2026-03-15T00:00:00",
      "end": "2026-03-15T01:00:00",
      "type": "task",
      "color": "#10b981",
      "description": "Daily brief: Morning_Brief_2026-03-15.md",
      "file": "Morning_Brief_2026-03-15.md",
      "id": "event-445341ea",
      "date": "2026-03-15",
      "source": "obsidian"
    },
    {
      "title": "Morning_Brief_2026-03-16",
      "start": "2026-03-16T00:00:00",
      "end": "2026-03-16T01:00:00",
      "type": "task",
      "color": "#10b981",
      "description": "Daily brief: Morning_Brief_2026-03-16.md",
      "file": "Morning_Brief_2026-03-16.md",
      "id": "event-2a044b46",
      "date": "2026-03-16",
      "source": "obsidian"
    },
    {
      "title": "Morning_Brief_2026-03-17",
      "start": "2026-03-17T00:00:00",
      "end": "2026-03-17T01:00:00",
      "type": "task",
      "color": "#10b981",
      "description": "Daily brief: Morning_Brief_2026-03-17.md",
      "file": "Morning_Brief_2026-03-17.md",
      "id": "event-b7563310",
      "date": "2026-03-17",
      "source": "obsidian"
    },
    {
      "title": "Morning_Brief_2026-03-18",
      "start": "2026-03-18T00:00:00",
      "end": "2026-03-18T01:00:00",
      "type": "task",
      "color": "#10b981",
      "description": "Daily brief: Morning_Brief_2026-03-18.md",
      "file": "Morning_Brief_2026-03-18.md",
      "id": "event-30355857",
      "date": "2026-03-18",
      "source": "obsidian"
    },
    {
      "id": "cal-3",
      "title": "Figma Template Review",
      "date": "2026-03-19",
      "type": "task",
      "color": "#f59e0b",
      "description": "Review Figma blueprint with Baro",
      "source": "manual"
    },
    {
      "title": "Morning_Brief_2026-03-19",
      "start": "2026-03-19T00:00:00",
      "end": "2026-03-19T01:00:00",
      "type": "task",
      "color": "#10b981",
      "description": "Daily brief: Morning_Brief_2026-03-19.md",
      "file": "Morning_Brief_2026-03-19.md",
      "id": "event-6f59df5f",
      "date": "2026-03-19",
      "source": "obsidian"
    },
    {
      "id": "cal-1",
      "title": "Weekly Review",
      "date": "2026-03-20",
      "type": "meeting",
      "color": "#10b981",
      "description": "Weekly team review and planning",
      "source": "manual"
    },
    {
      "title": "LIN_Report_2026-03-20",
      "start": "2026-03-20T00:00:00",
      "end": "2026-03-20T01:00:00",
      "type": "task",
      "color": "#10b981",
      "description": "Daily brief: LIN_Report_2026-03-20.md",
      "file": "LIN_Report_2026-03-20.md",
      "id": "event-590da489",
      "date": "2026-03-20",
      "source": "obsidian"
    },
    {
      "title": "WorkBlock_PM_Report_2026-03-20",
      "start": "2026-03-20T00:00:00",
      "end": "2026-03-20T01:00:00",
      "type": "task",
      "color": "#10b981",
      "description": "Daily brief: WorkBlock_PM_Report_2026-03-20.md",
      "file": "WorkBlock_PM_Report_2026-03-20.md",
      "id": "event-5b56c7a5",
      "date": "2026-03-20",
      "source": "obsidian"
    },
    {
      "title": "Morning Brief - Discord",
      "start": "2026-03-21T10:40:06.493770",
      "end": "2026-03-21T10:45:06.495431",
      "type": "cron",
      "color": "#3b82f6",
      "description": "Cron: 30 6 * * * (next run unknown)",
      "id": "event-5c66bf54",
      "date": "2026-03-21",
      "source": "openclaw"
    },
    {
      "title": "Regenerate Mission Control Calendar",
      "start": "2026-03-21T11:40:00",
      "end": "2026-03-21T11:45:00",
      "type": "cron",
      "color": "#3b82f6",
      "description": "Runs every 1.0 hours",
      "id": "event-fe79b927",
      "date": "2026-03-21",
      "source": "openclaw"
    },
    {
      "title": "Daily Check-in",
      "start": "2026-03-21T10:40:06.495874",
      "end": "2026-03-21T10:45:06.495875",
      "type": "cron",
      "color": "#3b82f6",
      "description": "Cron: 30 22 * * * (next run unknown)",
      "id": "event-9f5b98d8",
      "date": "2026-03-21",
      "source": "openclaw"
    },
    {
      "title": "Nightly Visual Diary Scan",
      "start": "2026-03-21T10:40:06.495878",
      "end": "2026-03-21T10:45:06.495879",
      "type": "cron",
      "color": "#3b82f6",
      "description": "Cron: 0 0 * * * (next run unknown)",
      "id": "event-75aa4b09",
      "date": "2026-03-21",
      "source": "openclaw"
    },
    {
      "title": "Bob Market Research - Passive Income Insights",
      "start": "2026-03-21T10:40:06.495883",
      "end": "2026-03-21T10:45:06.495884",
      "type": "cron",
      "color": "#3b82f6",
      "description": "Cron: 0 4 * * 6 (next run unknown)",
      "id": "event-37c3c14c",
      "date": "2026-03-21",
      "source": "openclaw"
    },
    {
      "title": "Morning Tech Report (6:35am)",
      "start": "2026-03-21T10:40:06.495887",
      "end": "2026-03-21T10:45:06.495888",
      "type": "cron",
      "color": "#3b82f6",
      "description": "Cron: 35 6 * * * (next run unknown)",
      "id": "event-46a0bd1e",
      "date": "2026-03-21",
      "source": "openclaw"
    },
    {
      "title": "LIN - Daily Social Trend Report",
      "start": "2026-03-21T10:40:06.495890",
      "end": "2026-03-21T10:45:06.495891",
      "type": "cron",
      "color": "#3b82f6",
      "description": "Cron: 0 7 * * * (next run unknown)",
      "id": "event-245d153d",
      "date": "2026-03-21",
      "source": "openclaw"
    },
    {
      "title": "LIN Report Summary - Discord Delivery",
      "start": "2026-03-21T10:40:06.495894",
      "end": "2026-03-21T10:45:06.495895",
      "type": "cron",
      "color": "#3b82f6",
      "description": "Cron: 10 7 * * * (next run unknown)",
      "id": "event-58626fa1",
      "date": "2026-03-21",
      "source": "openclaw"
    },
    {
      "title": "LIN Twitter Options - Discord Delivery",
      "start": "2026-03-21T10:40:06.495920",
      "end": "2026-03-21T10:45:06.495923",
      "type": "cron",
      "color": "#3b82f6",
      "description": "Cron: 15 5 * * * (next run unknown)",
      "id": "event-eef3e017",
      "date": "2026-03-21",
      "source": "openclaw"
    },
    {
      "title": "Project Vote - Morning Poll (7:30 AM)",
      "start": "2026-03-21T10:40:06.495978",
      "end": "2026-03-21T10:45:06.495980",
      "type": "cron",
      "color": "#3b82f6",
      "description": "Cron: 30 7 * * * (next run unknown)",
      "id": "event-0498a70e",
      "date": "2026-03-21",
      "source": "openclaw"
    },
    {
      "title": "Project Vote - Check and Set Priority (8:30 AM)",
      "start": "2026-03-21T10:40:06.495984",
      "end": "2026-03-21T10:45:06.495985",
      "type": "cron",
      "color": "#3b82f6",
      "description": "Cron: 30 8 * * * (next run unknown)",
      "id": "event-130707ff",
      "date": "2026-03-21",
      "source": "openclaw"
    },
    {
      "title": "Continuous Work - Check Progress (Every 2hrs)",
      "start": "2026-03-21T11:20:00",
      "end": "2026-03-21T11:25:00",
      "type": "cron",
      "color": "#3b82f6",
      "description": "Runs every 2.0 hours",
      "id": "event-350ed774",
      "date": "2026-03-21",
      "source": "openclaw"
    },
    {
      "title": "Afternoon Check-in (3:00 PM)",
      "start": "2026-03-21T10:40:06.495997",
      "end": "2026-03-21T10:45:06.496001",
      "type": "cron",
      "color": "#3b82f6",
      "description": "Cron: 0 15 * * * (next run unknown)",
      "id": "event-1716ccbb",
      "date": "2026-03-21",
      "source": "openclaw"
    },
    {
      "title": "Evening Check-in (9:00 PM)",
      "start": "2026-03-21T10:40:06.496016",
      "end": "2026-03-21T10:45:06.496017",
      "type": "cron",
      "color": "#3b82f6",
      "description": "Cron: 0 21 * * * (next run unknown)",
      "id": "event-078b9de3",
      "date": "2026-03-21",
      "source": "openclaw"
    },
    {
      "title": "Continuous Work - Check Progress & Advance (Every 2hrs)",
      "start": "2026-03-21T12:00:00",
      "end": "2026-03-21T12:05:00",
      "type": "cron",
      "color": "#3b82f6",
      "description": "Runs every 2.0 hours",
      "id": "event-602ef7dd",
      "date": "2026-03-21",
      "source": "openclaw"
    },
    {
      "title": "Bob_Research_2026-03-21",
      "start": "2026-03-21T00:00:00",
      "end": "2026-03-21T01:00:00",
      "type": "task",
      "color": "#10b981",
      "description": "Daily brief: Bob_Research_2026-03-21.md",
      "file": "Bob_Research_2026-03-21.md",
      "id": "event-750fb69c",
      "date": "2026-03-21",
      "source": "obsidian"
    },
    {
      "title": "Idea_Generation_2026-03-21",
      "start": "2026-03-21T00:00:00",
      "end": "2026-03-21T01:00:00",
      "type": "task",
      "color": "#10b981",
      "description": "Daily brief: Idea_Generation_2026-03-21.md",
      "file": "Idea_Generation_2026-03-21.md",
      "id": "event-34a8e7f7",
      "date": "2026-03-21",
      "source": "obsidian"
    },
    {
      "title": "LIN_Report_2026-03-21",
      "start": "2026-03-21T00:00:00",
      "end": "2026-03-21T01:00:00",
      "type": "task",
      "color": "#10b981",
      "description": "Daily brief: LIN_Report_2026-03-21.md",
      "file": "LIN_Report_2026-03-21.md",
      "id": "event-bd0f045a",
      "date": "2026-03-21",
      "source": "obsidian"
    },
    {
      "title": "LIN_Twitter_Options_2026-03-21",
      "start": "2026-03-21T00:00:00",
      "end": "2026-03-21T01:00:00",
      "type": "task",
      "color": "#10b981",
      "description": "Daily brief: LIN_Twitter_Options_2026-03-21.md",
      "file": "LIN_Twitter_Options_2026-03-21.md",
      "id": "event-b1a49e79",
      "date": "2026-03-21",
      "source": "obsidian"
    },
    {
      "title": "Morning_Brief_2026-03-21",
      "start": "2026-03-21T00:00:00",
      "end": "2026-03-21T01:00:00",
      "type": "task",
      "color": "#10b981",
      "description": "Daily brief: Morning_Brief_2026-03-21.md",
      "file": "Morning_Brief_2026-03-21.md",
      "id": "event-1c09741a",
      "date": "2026-03-21",
      "source": "obsidian"
    },
    {
      "id": "cal-2",
      "title": "Mission Control V0.6 Launch",
      "date": "2026-03-22",
      "type": "milestone",
      "color": "#8b5cf6",
      "description": "Launch calendar module for Mission Control",
      "source": "manual"
    }
  ],
  "generated_at": "2026-03-21T10:40:06.579830",
  "counts": {
    "manual": 3,
    "cron": 15,
    "obsidian": 14,
    "total": 32
  }
}